xenocanto.py
xeno_canto-2.0.3.dist-info/LICENSE
xeno_canto-2.0.3.dist-info/METADATA
xeno_canto-2.0.3.dist-info/WHEEL
xeno_canto-2.0.3.dist-info/entry_points.txt
xeno_canto-2.0.3.dist-info/top_level.txt
xeno_canto-2.0.3.dist-info/RECORD
