Metadata-Version: 2.1
Name: xeno-canto
Version: 2.0.3
Summary: xeno-canto.org API Wrapper
Home-page: https://github.com/ntivirikin/xeno-canto-py
Author: Nazariy Tivirikin
Author-email: n.tivirikin@gmail.com
License: MIT
License-File: LICENSE
